Workbook

Sheet Объекты
A1: Название объекта | B1: Адрес | C1: Заказчик | D1: Дата начала | E1: Дата сдачи | F1: Цена для клиента, € | G1: Аванс получен, € | H1: Остаток получен, € | I1: Расходы: материалы, € | J1: Расходы: бригада, € | K1: Расходы: утилизация / аренда, € | L1: Прочие расходы (инструмент и пр.), € | M1: Себестоимость, € | N1: Прибыль, € | O1: Маржа % | P1: Статус
A2: Vārnu iela 8 — коридоры | B2: Vārnu iela 8, Rīga | C2: DzīB "Vārnu iela 8, 8A, 8B, 8C" | E2: 46211 | F2: 2801 | G2: 1120.4 | H2: 1680.6 | I2: 800 | J2: 400 | K2: 0 | L2: 200 | M2: =IF(COUNT(I2:L2)=0,"",SUM(I2:L2)) | N2: =IF(F2="","",F2-SUM(I2:L2)) | O2: =IF(OR(F2="",F2=0),"",(F2-SUM(I2:L2))/F2) | P2: оплачен
M3: =IF(COUNT(I3:L3)=0,"",SUM(I3:L3)) | N3: =IF(F3="","",F3-SUM(I3:L3)) | O3: =IF(OR(F3="",F3=0),"",(F3-SUM(I3:L3))/F3)
M4: =IF(COUNT(I4:L4)=0,"",SUM(I4:L4)) | N4: =IF(F4="","",F4-SUM(I4:L4)) | O4: =IF(OR(F4="",F4=0),"",(F4-SUM(I4:L4))/F4)
M5: =IF(COUNT(I5:L5)=0,"",SUM(I5:L5)) | N5: =IF(F5="","",F5-SUM(I5:L5)) | O5: =IF(OR(F5="",F5=0),"",(F5-SUM(I5:L5))/F5)
M6: =IF(COUNT(I6:L6)=0,"",SUM(I6:L6)) | N6: =IF(F6="","",F6-SUM(I6:L6)) | O6: =IF(OR(F6="",F6=0),"",(F6-SUM(I6:L6))/F6)
M7: =IF(COUNT(I7:L7)=0,"",SUM(I7:L7)) | N7: =IF(F7="","",F7-SUM(I7:L7)) | O7: =IF(OR(F7="",F7=0),"",(F7-SUM(I7:L7))/F7)
M8: =IF(COUNT(I8:L8)=0,"",SUM(I8:L8)) | N8: =IF(F8="","",F8-SUM(I8:L8)) | O8: =IF(OR(F8="",F8=0),"",(F8-SUM(I8:L8))/F8)
M9: =IF(COUNT(I9:L9)=0,"",SUM(I9:L9)) | N9: =IF(F9="","",F9-SUM(I9:L9)) | O9: =IF(OR(F9="",F9=0),"",(F9-SUM(I9:L9))/F9)
M10: =IF(COUNT(I10:L10)=0,"",SUM(I10:L10)) | N10: =IF(F10="","",F10-SUM(I10:L10)) | O10: =IF(OR(F10="",F10=0),"",(F10-SUM(I10:L10))/F10)
M11: =IF(COUNT(I11:L11)=0,"",SUM(I11:L11)) | N11: =IF(F11="","",F11-SUM(I11:L11)) | O11: =IF(OR(F11="",F11=0),"",(F11-SUM(I11:L11))/F11)
M12: =IF(COUNT(I12:L12)=0,"",SUM(I12:L12)) | N12: =IF(F12="","",F12-SUM(I12:L12)) | O12: =IF(OR(F12="",F12=0),"",(F12-SUM(I12:L12))/F12)
M13: =IF(COUNT(I13:L13)=0,"",SUM(I13:L13)) | N13: =IF(F13="","",F13-SUM(I13:L13)) | O13: =IF(OR(F13="",F13=0),"",(F13-SUM(I13:L13))/F13)
M14: =IF(COUNT(I14:L14)=0,"",SUM(I14:L14)) | N14: =IF(F14="","",F14-SUM(I14:L14)) | O14: =IF(OR(F14="",F14=0),"",(F14-SUM(I14:L14))/F14)
... M31: =IF(COUNT(I31:L31)=0,"",SUM(I31:L31)) | N31: =IF(F31="","",F31-SUM(I31:L31)) | O31: =IF(OR(F31="",F31=0),"",(F31-SUM(I31:L31))/F31)
A32: ИТОГО: | F32: =SUM(F2:F31) | G32: =SUM(G2:G31) | H32: =SUM(H2:H31) | I32: =SUM(I2:I31) | J32: =SUM(J2:J31) | K32: =SUM(K2:K31) | L32: =SUM(L2:L31) | M32: =SUM(M2:M31) | N32: =SUM(N2:N31) | O32: =IF(F32=0,"",N32/F32)

Sheet Помесячно
A1: Сводка по месяцам 2026
A2: Объект попадает в месяц по дате сдачи (колонка «Дата сдачи» на листе Объекты).
A4: Месяц | B4: Оборот, € | C4: Расходы, € | D4: Прибыль, €
A5: Январь | B5: =SUMIFS(Объекты!$F$2:$F$31,Объекты!$E$2:$E$31,">="&DATE(2026,1,1),Объекты!$E$2:$E$31,"<"&DATE(2026,2,1)) | C5: =SUMIFS(Объекты!$I$2:$I$31,Объекты!$E$2:$E$31,">="&DATE(2026,1,1),Объекты!$E$2:$E$31,"<"&DATE(2026,2,1))+SUMIFS(Объекты!$J$2:$J$31,Объекты!$E$2:$E$31,">="&DATE(2026,1,1),Объекты!$E$2:$E$31,"<"&DATE(2026,2,1))+SUMIFS(Объекты!$K$2:$K$31,Объекты!$E$2:$E$31,">="&DATE(2026,1,1),Объекты!$E$2:$E$31,"<"&DATE(2026,2,1))+SUMIFS(Объекты!$L$2:$L$31,Объекты!$E$2:$E$31,">="&DATE(2026,1,1),Объекты!$E$2:$E$31,"<"&DATE(2026,2,1)) | D5: =B5-C5
A6: Февраль | B6: =SUMIFS(Объекты!$F$2:$F$31,Объекты!$E$2:$E$31,">="&DATE(2026,2,1),Объекты!$E$2:$E$31,"<"&DATE(2026,3,1)) | C6: =SUMIFS(Объекты!$I$2:$I$31,Объекты!$E$2:$E$31,">="&DATE(2026,2,1),Объекты!$E$2:$E$31,"<"&DATE(2026,3,1))+SUMIFS(Объекты!$J$2:$J$31,Объекты!$E$2:$E$31,">="&DATE(2026,2,1),Объекты!$E$2:$E$31,"<"&DATE(2026,3,1))+SUMIFS(Объекты!$K$2:$K$31,Объекты!$E$2:$E$31,">="&DATE(2026,2,1),Объекты!$E$2:$E$31,"<"&DATE(2026,3,1))+SUMIFS(Объекты!$L$2:$L$31,Объекты!$E$2:$E$31,">="&DATE(2026,2,1),Объекты!$E$2:$E$31,"<"&DATE(2026,3,1)) | D6: =B6-C6
A7: Март | B7: =SUMIFS(Объекты!$F$2:$F$31,Объекты!$E$2:$E$31,">="&DATE(2026,3,1),Объекты!$E$2:$E$31,"<"&DATE(2026,4,1)) | C7: =SUMIFS(Объекты!$I$2:$I$31,Объекты!$E$2:$E$31,">="&DATE(2026,3,1),Объекты!$E$2:$E$31,"<"&DATE(2026,4,1))+SUMIFS(Объекты!$J$2:$J$31,Объекты!$E$2:$E$31,">="&DATE(2026,3,1),Объекты!$E$2:$E$31,"<"&DATE(2026,4,1))+SUMIFS(Объекты!$K$2:$K$31,Объекты!$E$2:$E$31,">="&DATE(2026,3,1),Объекты!$E$2:$E$31,"<"&DATE(2026,4,1))+SUMIFS(Объекты!$L$2:$L$31,Объекты!$E$2:$E$31,">="&DATE(2026,3,1),Объекты!$E$2:$E$31,"<"&DATE(2026,4,1)) | D7: =B7-C7
A8: Апрель | B8: =SUMIFS(Объекты!$F$2:$F$31,Объекты!$E$2:$E$31,">="&DATE(2026,4,1),Объекты!$E$2:$E$31,"<"&DATE(2026,5,1)) | C8: =SUMIFS(Объекты!$I$2:$I$31,Объекты!$E$2:$E$31,">="&DATE(2026,4,1),Объекты!$E$2:$E$31,"<"&DATE(2026,5,1))+SUMIFS(Объекты!$J$2:$J$31,Объекты!$E$2:$E$31,">="&DATE(2026,4,1),Объекты!$E$2:$E$31,"<"&DATE(2026,5,1))+SUMIFS(Объекты!$K$2:$K$31,Объекты!$E$2:$E$31,">="&DATE(2026,4,1),Объекты!$E$2:$E$31,"<"&DATE(2026,5,1))+SUMIFS(Объекты!$L$2:$L$31,Объекты!$E$2:$E$31,">="&DATE(2026,4,1),Объекты!$E$2:$E$31,"<"&DATE(2026,5,1)) | D8: =B8-C8
A9: Май | B9: =SUMIFS(Объекты!$F$2:$F$31,Объекты!$E$2:$E$31,">="&DATE(2026,5,1),Объекты!$E$2:$E$31,"<"&DATE(2026,6,1)) | C9: =SUMIFS(Объекты!$I$2:$I$31,Объекты!$E$2:$E$31,">="&DATE(2026,5,1),Объекты!$E$2:$E$31,"<"&DATE(2026,6,1))+SUMIFS(Объекты!$J$2:$J$31,Объекты!$E$2:$E$31,">="&DATE(2026,5,1),Объекты!$E$2:$E$31,"<"&DATE(2026,6,1))+SUMIFS(Объекты!$K$2:$K$31,Объекты!$E$2:$E$31,">="&DATE(2026,5,1),Объекты!$E$2:$E$31,"<"&DATE(2026,6,1))+SUMIFS(Объекты!$L$2:$L$31,Объекты!$E$2:$E$31,">="&DATE(2026,5,1),Объекты!$E$2:$E$31,"<"&DATE(2026,6,1)) | D9: =B9-C9
A10: Июнь | B10: =SUMIFS(Объекты!$F$2:$F$31,Объекты!$E$2:$E$31,">="&DATE(2026,6,1),Объекты!$E$2:$E$31,"<"&DATE(2026,7,1)) | C10: =SUMIFS(Объекты!$I$2:$I$31,Объекты!$E$2:$E$31,">="&DATE(2026,6,1),Объекты!$E$2:$E$31,"<"&DATE(2026,7,1))+SUMIFS(Объекты!$J$2:$J$31,Объекты!$E$2:$E$31,">="&DATE(2026,6,1),Объекты!$E$2:$E$31,"<"&DATE(2026,7,1))+SUMIFS(Объекты!$K$2:$K$31,Объекты!$E$2:$E$31,">="&DATE(2026,6,1),Объекты!$E$2:$E$31,"<"&DATE(2026,7,1))+SUMIFS(Объекты!$L$2:$L$31,Объекты!$E$2:$E$31,">="&DATE(2026,6,1),Объекты!$E$2:$E$31,"<"&DATE(2026,7,1)) | D10: =B10-C10
A11: Июль | B11: =SUMIFS(Объекты!$F$2:$F$31,Объекты!$E$2:$E$31,">="&DATE(2026,7,1),Объекты!$E$2:$E$31,"<"&DATE(2026,8,1)) | C11: =SUMIFS(Объекты!$I$2:$I$31,Объекты!$E$2:$E$31,">="&DATE(2026,7,1),Объекты!$E$2:$E$31,"<"&DATE(2026,8,1))+SUMIFS(Объекты!$J$2:$J$31,Объекты!$E$2:$E$31,">="&DATE(2026,7,1),Объекты!$E$2:$E$31,"<"&DATE(2026,8,1))+SUMIFS(Объекты!$K$2:$K$31,Объекты!$E$2:$E$31,">="&DATE(2026,7,1),Объекты!$E$2:$E$31,"<"&DATE(2026,8,1))+SUMIFS(Объекты!$L$2:$L$31,Объекты!$E$2:$E$31,">="&DATE(2026,7,1),Объекты!$E$2:$E$31,"<"&DATE(2026,8,1)) | D11: =B11-C11
A12: Август | B12: =SUMIFS(Объекты!$F$2:$F$31,Объекты!$E$2:$E$31,">="&DATE(2026,8,1),Объекты!$E$2:$E$31,"<"&DATE(2026,9,1)) | C12: =SUMIFS(Объекты!$I$2:$I$31,Объекты!$E$2:$E$31,">="&DATE(2026,8,1),Объекты!$E$2:$E$31,"<"&DATE(2026,9,1))+SUMIFS(Объекты!$J$2:$J$31,Объекты!$E$2:$E$31,">="&DATE(2026,8,1),Объекты!$E$2:$E$31,"<"&DATE(2026,9,1))+SUMIFS(Объекты!$K$2:$K$31,Объекты!$E$2:$E$31,">="&DATE(2026,8,1),Объекты!$E$2:$E$31,"<"&DATE(2026,9,1))+SUMIFS(Объекты!$L$2:$L$31,Объекты!$E$2:$E$31,">="&DATE(2026,8,1),Объекты!$E$2:$E$31,"<"&DATE(2026,9,1)) | D12: =B12-C12
A13: Сентябрь | B13: =SUMIFS(Объекты!$F$2:$F$31,Объекты!$E$2:$E$31,">="&DATE(2026,9,1),Объекты!$E$2:$E$31,"<"&DATE(2026,10,1)) | C13: =SUMIFS(Объекты!$I$2:$I$31,Объекты!$E$2:$E$31,">="&DATE(2026,9,1),Объекты!$E$2:$E$31,"<"&DATE(2026,10,1))+SUMIFS(Объекты!$J$2:$J$31,Объекты!$E$2:$E$31,">="&DATE(2026,9,1),Объекты!$E$2:$E$31,"<"&DATE(2026,10,1))+SUMIFS(Объекты!$K$2:$K$31,Объекты!$E$2:$E$31,">="&DATE(2026,9,1),Объекты!$E$2:$E$31,"<"&DATE(2026,10,1))+SUMIFS(Объекты!$L$2:$L$31,Объекты!$E$2:$E$31,">="&DATE(2026,9,1),Объекты!$E$2:$E$31,"<"&DATE(2026,10,1)) | D13: =B13-C13
A14: Октябрь | B14: =SUMIFS(Объекты!$F$2:$F$31,Объекты!$E$2:$E$31,">="&DATE(2026,10,1),Объекты!$E$2:$E$31,"<"&DATE(2026,11,1)) | C14: =SUMIFS(Объекты!$I$2:$I$31,Объекты!$E$2:$E$31,">="&DATE(2026,10,1),Объекты!$E$2:$E$31,"<"&DATE(2026,11,1))+SUMIFS(Объекты!$J$2:$J$31,Объекты!$E$2:$E$31,">="&DATE(2026,10,1),Объекты!$E$2:$E$31,"<"&DATE(2026,11,1))+SUMIFS(Объекты!$K$2:$K$31,Объекты!$E$2:$E$31,">="&DATE(2026,10,1),Объекты!$E$2:$E$31,"<"&DATE(2026,11,1))+SUMIFS(Объекты!$L$2:$L$31,Объекты!$E$2:$E$31,">="&DATE(2026,10,1),Объекты!$E$2:$E$31,"<"&DATE(2026,11,1)) | D14: =B14-C14
A15: Ноябрь | B15: =SUMIFS(Объекты!$F$2:$F$31,Объекты!$E$2:$E$31,">="&DATE(2026,11,1),Объекты!$E$2:$E$31,"<"&DATE(2026,12,1)) | C15: =SUMIFS(Объекты!$I$2:$I$31,Объекты!$E$2:$E$31,">="&DATE(2026,11,1),Объекты!$E$2:$E$31,"<"&DATE(2026,12,1))+SUMIFS(Объекты!$J$2:$J$31,Объекты!$E$2:$E$31,">="&DATE(2026,11,1),Объекты!$E$2:$E$31,"<"&DATE(2026,12,1))+SUMIFS(Объекты!$K$2:$K$31,Объекты!$E$2:$E$31,">="&DATE(2026,11,1),Объекты!$E$2:$E$31,"<"&DATE(2026,12,1))+SUMIFS(Объекты!$L$2:$L$31,Объекты!$E$2:$E$31,">="&DATE(2026,11,1),Объекты!$E$2:$E$31,"<"&DATE(2026,12,1)) | D15: =B15-C15
A16: Декабрь | B16: =SUMIFS(Объекты!$F$2:$F$31,Объекты!$E$2:$E$31,">="&DATE(2026,12,1),Объекты!$E$2:$E$31,"<"&DATE(2026,13,1)) | C16: =SUMIFS(Объекты!$I$2:$I$31,Объекты!$E$2:$E$31,">="&DATE(2026,12,1),Объекты!$E$2:$E$31,"<"&DATE(2026,13,1))+SUMIFS(Объекты!$J$2:$J$31,Объекты!$E$2:$E$31,">="&DATE(2026,12,1),Объекты!$E$2:$E$31,"<"&DATE(2026,13,1))+SUMIFS(Объекты!$K$2:$K$31,Объекты!$E$2:$E$31,">="&DATE(2026,12,1),Объекты!$E$2:$E$31,"<"&DATE(2026,13,1))+SUMIFS(Объекты!$L$2:$L$31,Объекты!$E$2:$E$31,">="&DATE(2026,12,1),Объекты!$E$2:$E$31,"<"&DATE(2026,13,1)) | D16: =B16-C16
A17: ИТОГО 2026: | B17: =SUM(B5:B16) | C17: =SUM(C5:C16) | D17: =SUM(D5:D16)

Sheet Подушка
A1: Подушка безопасности (резерв)
A2: Плюс — отложил в резерв, минус — взял из резерва.
A4: Отложено сейчас: | B4: =SUM(B7:B106)
A6: Дата | B6: Сумма, € (+/−) | C6: Комментарий | D6: Остаток, €
A7: 46211 | B7: 0 | C7: Стартовый остаток | D7: =IF(B7="","",SUM($B$7:B7))
D8: =IF(B8="","",SUM($B$7:B8))
D9: =IF(B9="","",SUM($B$7:B9))
D10: =IF(B10="","",SUM($B$7:B10))
D11: =IF(B11="","",SUM($B$7:B11))
D12: =IF(B12="","",SUM($B$7:B12))
D13: =IF(B13="","",SUM($B$7:B13))
D14: =IF(B14="","",SUM($B$7:B14))
D15: =IF(B15="","",SUM($B$7:B15))
D16: =IF(B16="","",SUM($B$7:B16))
D17: =IF(B17="","",SUM($B$7:B17))
D18: =IF(B18="","",SUM($B$7:B18))
D19: =IF(B19="","",SUM($B$7:B19))
... D106: =IF(B106="","",SUM($B$7:B106))
